{"v":5,"entries":{"example-blogcard--docs":{"id":"example-blogcard--docs","title":"Example/BlogCard","name":"Docs","importPath":"./src/stories/BlogCard.stories.tsx","type":"docs","tags":["dev","test","autodocs"],"storiesImports":[]},"example-blogcard--default":{"type":"story","id":"example-blogcard--default","name":"Default","title":"Example/BlogCard","importPath":"./src/stories/BlogCard.stories.tsx","componentPath":"./src/BlogCard.tsx","tags":["dev","test","autodocs"]},"example-blogcard--with-image":{"type":"story","id":"example-blogcard--with-image","name":"With Image","title":"Example/BlogCard","importPath":"./src/stories/BlogCard.stories.tsx","componentPath":"./src/BlogCard.tsx","tags":["dev","test","autodocs"]},"example-blogcard--with-tags":{"type":"story","id":"example-blogcard--with-tags","name":"With Tags","title":"Example/BlogCard","importPath":"./src/stories/BlogCard.stories.tsx","componentPath":"./src/BlogCard.tsx","tags":["dev","test","autodocs"]},"example-blogcard--with-tags-and-image":{"type":"story","id":"example-blogcard--with-tags-and-image","name":"With Tags And Image","title":"Example/BlogCard","importPath":"./src/stories/BlogCard.stories.tsx","componentPath":"./src/BlogCard.tsx","tags":["dev","test","autodocs"]},"example-blogcard--with-tags-and-wide-image":{"type":"story","id":"example-blogcard--with-tags-and-wide-image","name":"With Tags And Wide Image","title":"Example/BlogCard","importPath":"./src/stories/BlogCard.stories.tsx","componentPath":"./src/BlogCard.tsx","tags":["dev","test","autodocs"]},"example-blogcard--with-tags-and-wide-image-and-color":{"type":"story","id":"example-blogcard--with-tags-and-wide-image-and-color","name":"With Tags And Wide Image And Color","title":"Example/BlogCard","importPath":"./src/stories/BlogCard.stories.tsx","componentPath":"./src/BlogCard.tsx","tags":["dev","test","autodocs"]},"example-blogcard--with-published-date":{"type":"story","id":"example-blogcard--with-published-date","name":"With Published Date","title":"Example/BlogCard","importPath":"./src/stories/BlogCard.stories.tsx","componentPath":"./src/BlogCard.tsx","tags":["dev","test","autodocs"]},"layout-equalspacinggrid--docs":{"id":"layout-equalspacinggrid--docs","title":"Layout/EqualSpacingGrid","name":"Docs","importPath":"./src/stories/EqualSpacingGrid.stories.tsx","type":"docs","tags":["dev","test","autodocs"],"storiesImports":[]},"layout-equalspacinggrid--default":{"type":"story","id":"layout-equalspacinggrid--default","name":"Default","title":"Layout/EqualSpacingGrid","importPath":"./src/stories/EqualSpacingGrid.stories.tsx","componentPath":"./src/EqualSpacingGrid.tsx","tags":["dev","test","autodocs"]},"layout-equalspacinggrid--four-columns":{"type":"story","id":"layout-equalspacinggrid--four-columns","name":"Four Columns","title":"Layout/EqualSpacingGrid","importPath":"./src/stories/EqualSpacingGrid.stories.tsx","componentPath":"./src/EqualSpacingGrid.tsx","tags":["dev","test","autodocs"]},"layout-equalspacinggrid--with-different-spacing":{"type":"story","id":"layout-equalspacinggrid--with-different-spacing","name":"With Different Spacing","title":"Layout/EqualSpacingGrid","importPath":"./src/stories/EqualSpacingGrid.stories.tsx","componentPath":"./src/EqualSpacingGrid.tsx","tags":["dev","test","autodocs"]},"layout-equalspacinggrid--two-columns":{"type":"story","id":"layout-equalspacinggrid--two-columns","name":"Two Columns","title":"Layout/EqualSpacingGrid","importPath":"./src/stories/EqualSpacingGrid.stories.tsx","componentPath":"./src/EqualSpacingGrid.tsx","tags":["dev","test","autodocs"]}}}
